nopo/__init__.py
nopo/by.py
nopo/el.py
nopo/el_parent.py
nopo/els.py
nopo/pg.py
nopo-1.3.1.dist-info/LICENSE
nopo-1.3.1.dist-info/METADATA
nopo-1.3.1.dist-info/WHEEL
nopo-1.3.1.dist-info/top_level.txt
nopo-1.3.1.dist-info/RECORD
