Metadata-Version: 2.1
Name: nopo
Version: 1.3.1
Summary: not only page object: A package for Page Object Model (POM), a tool based on Selenium that helps you build POM in web test.
Home-page: https://github.com/DingJunyao/nopo
Author: DingJunyao
Author-email: dingjunyao0703@163.com
Project-URL: Source, https://github.com/DingJunyao/nopo
Project-URL: Bug Tracker, https://github.com/DingJunyao/nopo/issues
Classifier: Programming Language :: Python :: 3
Classifier: License :: OSI Approved :: Apache Software License
Classifier: Operating System :: OS Independent
Classifier: Topic :: Software Development :: Testing
Classifier: Topic :: Software Development :: Libraries
Requires-Python: >=3.7
License-File: LICENSE
Requires-Dist: cssselect
Requires-Dist: selenium
